cloudops/__init__.py
cloudops/secret_manager/__init__.py
cloudops/secret_manager/google/__init__.py
cloudops/secret_manager/google/secret.py
cloudops_secret_manager_google-0.1.1.dist-info/METADATA
cloudops_secret_manager_google-0.1.1.dist-info/WHEEL
cloudops_secret_manager_google-0.1.1.dist-info/RECORD
